ipgw/__init__.py
ipgw/cli/__init__.py
ipgw/cli/arguments.py
ipgw/cli/get_info.py
ipgw/cli/ipgw.py
ipgw/cli/print_status.py
ipgw/core/__init__.py
ipgw/core/config.py
ipgw/core/errors_modals.py
ipgw/core/ipgw.py
ipgw/core/prepare_session.py
ipgw/core/api/SSO.py
ipgw/core/api/SSO_error.py
ipgw/core/api/__init__.py
ipgw/core/api/portal.py
ipgw/core/api/portal_error.py
NEU_ipgw_manager-3.2.dist-info/LICENSE
NEU_ipgw_manager-3.2.dist-info/METADATA
NEU_ipgw_manager-3.2.dist-info/WHEEL
NEU_ipgw_manager-3.2.dist-info/entry_points.txt
NEU_ipgw_manager-3.2.dist-info/top_level.txt
NEU_ipgw_manager-3.2.dist-info/RECORD
