Metadata-Version: 2.1
Name: NEU-ipgw-manager
Version: 3.2
Summary: ipgw manager for NEU network gateway
Author-email: Neboer <rubinposter@gmail.com>
License: MIT
Keywords: NEU,东北大学,ipgw,网关,northeastern university
Classifier: Development Status :: 5 - Production/Stable
Classifier: Intended Audience :: End Users/Desktop
Classifier: Operating System :: OS Independent
Classifier: Environment :: Console
Classifier: Natural Language :: Chinese (Simplified)
Classifier: Topic :: Internet :: WWW/HTTP
Classifier: Topic :: Utilities
Classifier: Programming Language :: Python
Classifier: Programming Language :: Python :: 3
Classifier: Programming Language :: Python :: 3 :: Only
Classifier: Programming Language :: Python :: 3.7
Classifier: Programming Language :: Python :: 3.8
Classifier: Programming Language :: Python :: 3.9
Classifier: Programming Language :: Python :: 3.10
Classifier: Programming Language :: Python :: 3.11
Classifier: Programming Language :: Python :: 3.12
Classifier: Programming Language :: Python :: 3.13
Classifier: Programming Language :: Python :: 3.14
Requires-Python: >=3.7
License-File: LICENSE
Requires-Dist: requests
Requires-Dist: tabulate
Requires-Dist: beautifulsoup4
Requires-Dist: wcwidth
Requires-Dist: platformdirs
